graphai/__init__.py
graphai/analyzer.py
graphai/plotter.py
graphai/recommender.py
graphai/themes.py
timeanalisespro-0.1.dist-info/METADATA
timeanalisespro-0.1.dist-info/WHEEL
timeanalisespro-0.1.dist-info/top_level.txt
timeanalisespro-0.1.dist-info/RECORD
